odoo/addons/account_move_tier_validation_approver/README.rst
odoo/addons/account_move_tier_validation_approver/__init__.py
odoo/addons/account_move_tier_validation_approver/__manifest__.py
odoo/addons/account_move_tier_validation_approver/i18n/account_move_tier_validation_approver.pot
odoo/addons/account_move_tier_validation_approver/i18n/es_PA.po
odoo/addons/account_move_tier_validation_approver/i18n/it.po
odoo/addons/account_move_tier_validation_approver/models/__init__.py
odoo/addons/account_move_tier_validation_approver/models/account_move.py
odoo/addons/account_move_tier_validation_approver/models/res_company.py
odoo/addons/account_move_tier_validation_approver/models/res_config_settings.py
odoo/addons/account_move_tier_validation_approver/models/res_partner.py
odoo/addons/account_move_tier_validation_approver/readme/CONFIGURE.md
odoo/addons/account_move_tier_validation_approver/readme/CONTRIBUTORS.md
odoo/addons/account_move_tier_validation_approver/readme/DESCRIPTION.md
odoo/addons/account_move_tier_validation_approver/readme/USAGE.md
odoo/addons/account_move_tier_validation_approver/static/description/icon.png
odoo/addons/account_move_tier_validation_approver/static/description/index.html
odoo/addons/account_move_tier_validation_approver/tests/__init__.py
odoo/addons/account_move_tier_validation_approver/tests/test_account_move_tier_validation_approver.py
odoo/addons/account_move_tier_validation_approver/views/account_move_views.xml
odoo/addons/account_move_tier_validation_approver/views/res_config_settings_views.xml
odoo/addons/account_move_tier_validation_approver/views/res_partner_views.xml
odoo_addon_account_move_tier_validation_approver-18.0.1.0.0.5.dist-info/METADATA
odoo_addon_account_move_tier_validation_approver-18.0.1.0.0.5.dist-info/WHEEL
odoo_addon_account_move_tier_validation_approver-18.0.1.0.0.5.dist-info/top_level.txt
odoo_addon_account_move_tier_validation_approver-18.0.1.0.0.5.dist-info/RECORD
